pyawaitable/__init__.py
pyawaitable/__main__.py
hatch_autorun_pyawaitable.pth
pyawaitable/pyawaitable.h
pyawaitable-2.0.1.dist-info/METADATA
pyawaitable-2.0.1.dist-info/WHEEL
pyawaitable-2.0.1.dist-info/entry_points.txt
pyawaitable-2.0.1.dist-info/licenses/LICENSE
pyawaitable-2.0.1.dist-info/RECORD
