Metadata-Version: 2.4
Name: pyawaitable
Version: 2.0.1
Summary: Call asynchronous code from an extension module.
Project-URL: Documentation, https://pyawaitable.zintensity.dev
Project-URL: Issues, https://github.com/ZeroIntensity/pyawaitable/issues
Project-URL: Source, https://github.com/ZeroIntensity/pyawaitable
Author-email: Peter Bierma <zintensitydev@gmail.com>
License: MIT License
License-File: LICENSE
Classifier: Programming Language :: Python
Classifier: Programming Language :: Python :: 3.9
Classifier: Programming Language :: Python :: 3.10
Classifier: Programming Language :: Python :: 3.11
Classifier: Programming Language :: Python :: 3.12
Classifier: Programming Language :: Python :: 3.13
Classifier: Programming Language :: Python :: Implementation :: CPython
Requires-Python: >=3.9
